{
  "generator-jhipster": {
    "authenticationType": "jwt",
    "cacheProvider": "hazelcast",
    "serverPort": "8093",
    "serviceDiscoveryType": "consul",
    "skipUserManagement": true,
    "baseName": "datasource",
    "buildTool": "maven",
    "databaseType": "sql",
    "devDatabaseType": "postgresql",
    "enableHibernateCache": true,
    "enableSwaggerCodegen": false,
    "enableTranslation": true,
    "jhiPrefix": "jhi",
    "languages": [
      "en",
      "fr"
    ],
    "messageBroker": false,
    "nativeLanguage": "en",
    "prodDatabaseType": "postgresql",
    "searchEngine": false,
    "skipClient": true,
    "testFrameworks": [],
    "websocket": false,
    "packageName": "com.onecreation.api.datasource",
    "packageFolder": "com/onecreation/api/datasource",
    "applicationType": "microservice",
    "jhipsterVersion": "6.9.1",
    "creationTimestamp": 1592767800282,
    "clientPackageManager": "npm"
  },
  "entities": [
    "DataSource",
    "Template"
  ]
}
